flask_shield
