Metadata-Version: 1.1
Name: Flask-Shield
Version: 0.2.2
Summary: Flask-Shield is an extension of Flask for permission management based on RBAC.
Home-page: https://github.com/fengluo/flask-shield
Author: fengluo
Author-email: fengluo17@gmail.com
License: MIT
Platform: any
Classifier: Environment :: Web Environment
Classifier: Intended Audience :: Developers
Classifier: License :: OSI Approved :: MIT License
Classifier: Operating System :: OS Independent
Classifier: Programming Language :: Python
Classifier: Topic :: Internet :: WWW/HTTP :: Dynamic Content
Classifier: Topic :: Software Development :: Libraries :: Python Modules
